pivotal_parser/__init__.py
pivotal_parser/cli.py
pivotal_parser-0.1.0.dist-info/entry_points.txt
pivotal_parser-0.1.0.dist-info/WHEEL
pivotal_parser-0.1.0.dist-info/METADATA
pivotal_parser-0.1.0.dist-info/RECORD
